{
  "version": 1,
  "bed": {
    "widthX": 0.21,
    "lengthZ": 0.61,
    "wallHeight": 0.06
  },
  "cargo": [
    {
      "type": "박스 B-007",
      "localPos": {
        "x": 0.07515679660998895,
        "y": 0.035,
        "z": 0.12860406715166203
      },
      "localEuler": {
        "x": 0,
        "y": 90
      },
      "secured": true
    },
    {
      "type": "박스 B-006",
      "localPos": {
        "x": 0.08145322106487057,
        "y": 0.095,
        "z": 0.061081222594789326
      },
      "localEuler": {
        "x": 0,
        "y": 0
      },
      "secured": true
    },
    {
      "type": "박스 B-006",
      "localPos": {
        "x": 0.09023711096545337,
        "y": 0.095,
        "z": 0.22131890056946468
      },
      "localEuler": {
        "x": 0,
        "y": 0
      },
      "secured": true
    },
    {
      "type": "박스 B-005",
      "localPos": {
        "x": 0.044791765797992295,
        "y": 0.18,
        "z": 0.044692832903662896
      },
      "localEuler": {
        "x": 0,
        "y": 90
      },
      "secured": true
    },
    {
      "type": "박스 B-005",
      "localPos": {
        "x": 0.06437793895737602,
        "y": 0.060000000000000005,
        "z": 0.3794016632948696
      },
      "localEuler": {
        "x": 0,
        "y": 90
      },
      "secured": true
    },
    {
      "type": "박스 B-002",
      "localPos": {
        "x": 0.1108914817313542,
        "y": 0.14500000000000002,
        "z": 0.19396078446982834
      },
      "localEuler": {
        "x": 0,
        "y": 0
      },
      "secured": true
    },
    {
      "type": "박스 B-002",
      "localPos": {
        "x": 0.08842146557005773,
        "y": 0.025,
        "z": 0.5102838383335528
      },
      "localEuler": {
        "x": 0,
        "y": 0
      },
      "secured": true
    },
    {
      "type": "박스 B-003",
      "localPos": {
        "x": 0.07551284772683538,
        "y": 0.06,
        "z": 0.5094829203424072
      },
      "localEuler": {
        "x": 0,
        "y": 0
      },
      "secured": true
    },
    {
      "type": "합성 경량소형",
      "localPos": {
        "x": 0.14952709144817586,
        "y": 0.16,
        "z": 0.07736189855781546
      },
      "localEuler": {
        "x": 0,
        "y": 0
      },
      "secured": true
    }
  ]
}